boatd-1.1.4.dist-info/DESCRIPTION.rst
boatd-1.1.4.dist-info/top_level.txt
boatd-1.1.4.dist-info/RECORD
boatd-1.1.4.dist-info/METADATA
boatd-1.1.4.dist-info/WHEEL
boatd-1.1.4.dist-info/metadata.json
boatd-1.1.4.data/scripts/boatd-start
boatd/nmea.py
boatd/plugin.py
boatd/color.py
boatd/api.py
boatd/__init__.py
boatd/config.py
boatd/logging.py
boatd/driver.py
boatd/boat.py
